Xgua/__init__.py
Xgua/config.py
Xgua/logger.py
Xgua/models/__init__.py
Xgua/models/log.py
Xgua/processing/__init__.py
Xgua/processing/upload.py
Xgua/s3/__init__.py
Xgua/s3/client.py
Xgua-0.0.2.dist-info/METADATA
Xgua-0.0.2.dist-info/WHEEL
Xgua-0.0.2.dist-info/top_level.txt
Xgua-0.0.2.dist-info/RECORD
