Metadata-Version: 2.1
Name: Xgua
Version: 0.0.2
Summary: Logger with saving logs to s3 storage
Home-page: https://github.com/SikWeet/Xgua
Author: Xpeawey
Author-email: girectx@gmail.com
Project-URL: GitHub, https://github.com/SikWeet/Xgua
Keywords: Xgua Logger S3 s3logger
Classifier: Programming Language :: Python :: 3.11
Classifier: License :: OSI Approved :: MIT License
Classifier: Operating System :: OS Independent
Requires-Python: >=3.6
